aabpl/__init__.py
aabpl/main.py
aabpl/random_distribution.py
aabpl/valid_area.py
aabpl/doc/__init__.py
aabpl/doc/docstrings.py
aabpl/illustrations/__init__.py
aabpl/illustrations/distribution_plot.py
aabpl/illustrations/grid.py
aabpl/illustrations/illustrate_cell_pattern.py
aabpl/illustrations/illustrate_nested_grid.py
aabpl/illustrations/illustrate_optimal_grid_spacing.py
aabpl/illustrations/illustrate_point_to_cell_region_assignment.py
aabpl/illustrations/illustrate_point_to_disk.py
aabpl/illustrations/illustrate_sample_area.py
aabpl/illustrations/plot_pt_vars.py
aabpl/illustrations/plot_utils.py
aabpl/illustrations/visualize_pt_to_cell_region_assignment.py
aabpl/radius_search/__init__.py
aabpl/radius_search/clusters.py
aabpl/radius_search/grid_class.py
aabpl/radius_search/nested_search.py
aabpl/radius_search/offset_region_classes.py
aabpl/radius_search/offset_regions.py
aabpl/radius_search/optimal_grid_spacing.py
aabpl/radius_search/pts_radius_search.py
aabpl/radius_search/pts_to_cells.py
aabpl/radius_search/pts_to_offset_regions.py
aabpl/radius_search/radius_search_class.py
aabpl/radius_search/two_dimensional_weak_ordering_class.py
aabpl/testing/__init__.py
aabpl/testing/test_performance.py
aabpl/utils/__init__.py
aabpl/utils/crs_transformation.py
aabpl/utils/distances_to_cell.py
aabpl/utils/general.py
aabpl/utils/intersections.py
aabpl/utils/precision.py
aabpl/utils/rotations.py
aabpl-0.2.14.dist-info/LICENSE
aabpl-0.2.14.dist-info/METADATA
aabpl-0.2.14.dist-info/WHEEL
aabpl-0.2.14.dist-info/top_level.txt
aabpl-0.2.14.dist-info/RECORD
